odoo/addons/crm_claim/README.rst
odoo/addons/crm_claim/__init__.py
odoo/addons/crm_claim/__manifest__.py
odoo/addons/crm_claim/data/crm_claim_data.xml
odoo/addons/crm_claim/demo/crm_claim_demo.xml
odoo/addons/crm_claim/i18n/crm_claim.pot
odoo/addons/crm_claim/i18n/de.po
odoo/addons/crm_claim/i18n/es.po
odoo/addons/crm_claim/i18n/es_CO.po
odoo/addons/crm_claim/i18n/gl.po
odoo/addons/crm_claim/i18n/hr.po
odoo/addons/crm_claim/i18n/pt_BR.po
odoo/addons/crm_claim/i18n/tr.po
odoo/addons/crm_claim/models/__init__.py
odoo/addons/crm_claim/models/crm_claim.py
odoo/addons/crm_claim/models/crm_claim_category.py
odoo/addons/crm_claim/models/crm_claim_stage.py
odoo/addons/crm_claim/models/res_partner.py
odoo/addons/crm_claim/readme/CONFIGURE.rst
odoo/addons/crm_claim/readme/CONTRIBUTORS.rst
odoo/addons/crm_claim/readme/DESCRIPTION.rst
odoo/addons/crm_claim/readme/HISTORY.rst
odoo/addons/crm_claim/readme/USAGE.rst
odoo/addons/crm_claim/report/__init__.py
odoo/addons/crm_claim/report/crm_claim_report.py
odoo/addons/crm_claim/report/crm_claim_report_view.xml
odoo/addons/crm_claim/security/crm_claim_security.xml
odoo/addons/crm_claim/security/ir.model.access.csv
odoo/addons/crm_claim/static/description/icon.png
odoo/addons/crm_claim/static/description/index.html
odoo/addons/crm_claim/tests/__init__.py
odoo/addons/crm_claim/tests/test_crm_claim.py
odoo/addons/crm_claim/views/crm_claim_category_views.xml
odoo/addons/crm_claim/views/crm_claim_menu.xml
odoo/addons/crm_claim/views/crm_claim_stage_views.xml
odoo/addons/crm_claim/views/crm_claim_views.xml
odoo/addons/crm_claim/views/res_partner_views.xml
odoo13_addon_crm_claim-13.0.1.1.0.dist-info/METADATA
odoo13_addon_crm_claim-13.0.1.1.0.dist-info/WHEEL
odoo13_addon_crm_claim-13.0.1.1.0.dist-info/top_level.txt
odoo13_addon_crm_claim-13.0.1.1.0.dist-info/RECORD
